easywatch/__init__.py
easywatch/easywatch.py
easywatch-0.0.5.dist-info/LICENSE.txt
easywatch-0.0.5.dist-info/METADATA
easywatch-0.0.5.dist-info/RECORD
easywatch-0.0.5.dist-info/WHEEL
easywatch-0.0.5.dist-info/top_level.txt
